gordon_introspection/__init__.py
gordon_introspection/app.py
gordon_introspection/views.py
gordon_introspection-0.1.3.dist-info/LICENSE.txt
gordon_introspection-0.1.3.dist-info/METADATA
gordon_introspection-0.1.3.dist-info/RECORD
gordon_introspection-0.1.3.dist-info/WHEEL
gordon_introspection-0.1.3.dist-info/entry_points.txt
gordon_introspection-0.1.3.dist-info/top_level.txt
