Metadata-Version: 2.1
Name: gordon-introspection
Version: 0.1.3
Summary: Gordon DNS Introspection Server
Home-page: https://github.com/spotify/gordon-introspection
Author: Lynn Root
Author-email: lynn@spotify.com
Maintainer: Lynn Root
Maintainer-email: lynn@spotify.com
License: Apache 2.0
Keywords: dns
Platform: UNKNOWN
Classifier: Development Status :: 2 - Pre-Alpha
Classifier: License :: OSI Approved :: Apache Software License
Classifier: Natural Language :: English
Classifier: Operating System :: POSIX :: Linux
Classifier: Operating System :: MacOS :: MacOS X
Classifier: Programming Language :: Python
Classifier: Programming Language :: Python :: 3
Classifier: Programming Language :: Python :: 3.6
Classifier: Programming Language :: Python :: Implementation :: CPython
Requires-Dist: aiohttp
Requires-Dist: attrs
Requires-Dist: gordon-dns
Requires-Dist: setuptools
Requires-Dist: zope.interface
